fastapi_async_sqlalchemy/__init__.py
fastapi_async_sqlalchemy/exceptions.py
fastapi_async_sqlalchemy/middleware.py
fastapi_async_sqlalchemy/py.typed
fastapi_async_sqlalchemy-0.7.1.dist-info/licenses/LICENSE
fastapi_async_sqlalchemy-0.7.1.dist-info/METADATA
fastapi_async_sqlalchemy-0.7.1.dist-info/WHEEL
fastapi_async_sqlalchemy-0.7.1.dist-info/top_level.txt
fastapi_async_sqlalchemy-0.7.1.dist-info/RECORD
