Metadata-Version: 2.4
Name: fastapi-async-sqlalchemy
Version: 0.7.1
Summary: SQLAlchemy middleware for FastAPI
Home-page: https://github.com/h0rn3t/fastapi-async-sqlalchemy.git
Author: Eugene Shershen
Author-email: h0rn3t.null@gmail.com
License: MIT
Project-URL: Code, https://github.com/h0rn3t/fastapi-async-sqlalchemy
Project-URL: Issue tracker, https://github.com/h0rn3t/fastapi-async-sqlalchemy/issues
Classifier: Development Status :: 5 - Production/Stable
Classifier: Environment :: Web Environment
Classifier: Framework :: AsyncIO
Classifier: Intended Audience :: Developers
Classifier: License :: OSI Approved :: MIT License
Classifier: Operating System :: OS Independent
Classifier: Programming Language :: Python :: 3.7
Classifier: Programming Language :: Python :: 3.8
Classifier: Programming Language :: Python :: 3.9
Classifier: Programming Language :: Python :: 3.10
Classifier: Programming Language :: Python :: 3.11
Classifier: Programming Language :: Python :: 3.12
Classifier: Programming Language :: Python :: 3 :: Only
Classifier: Programming Language :: Python :: Implementation :: CPython
Classifier: Topic :: Internet :: WWW/HTTP :: HTTP Servers
Classifier: Topic :: Internet :: WWW/HTTP :: Dynamic Content
Classifier: Topic :: Software Development :: Libraries :: Python Modules
Requires-Python: >=3.7
License-File: LICENSE
Requires-Dist: starlette>=0.13.6
Requires-Dist: SQLAlchemy>=1.4.19
Dynamic: author
Dynamic: author-email
Dynamic: classifier
Dynamic: description
Dynamic: description-content-type
Dynamic: home-page
Dynamic: license
Dynamic: license-file
Dynamic: project-url
Dynamic: requires-dist
Dynamic: requires-python
Dynamic: summary
